dnspace.py
dnspace-0.1.0.dist-info/DESCRIPTION.rst
dnspace-0.1.0.dist-info/METADATA
dnspace-0.1.0.dist-info/RECORD
dnspace-0.1.0.dist-info/WHEEL
dnspace-0.1.0.dist-info/entry_points.txt
dnspace-0.1.0.dist-info/metadata.json
dnspace-0.1.0.dist-info/top_level.txt
