Metadata-Version: 2.0
Name: dnspace
Version: 0.1.0
Summary: docs need space
Home-page: https://github.com/chenjiandongx/docs-need-space
Author: chenjiandongx
Author-email: chenjiandongx@qq.com
License: MIT
Platform: UNKNOWN
